icon/__init__.py
icon/lockBlack.png
icon/lockGreen.png
icon/lockRed.png
icon/lockWithe.png
pkexec/__init__.py
pkexec/down.policy
pkexec/post-down.policy
pkexec/post-up.policy
pkexec/up.policy
snxtray-0.0.7.data/data/icon/lockGreen.png
snxtray-0.0.7.data/data/icon/lockRed.png
snxtray-0.0.7.data/data/icon/lockWithe.png
snxtray-0.0.7.data/data/pkexec/down.policy
snxtray-0.0.7.data/data/pkexec/post-down.policy
snxtray-0.0.7.data/data/pkexec/post-up.policy
snxtray-0.0.7.data/data/pkexec/up.policy
snxtray-0.0.7.data/scripts/snxtray
test/__init__.py
test/mock_popen.py
test/test_executable.py
test/test_hooks.py
utils/__init__.py
utils/config.py
utils/snx.py
windows/Configure.py
windows/__init__.py
wxUI/__init__.py
wxUI/task_bar_icon.py
snxtray-0.0.7.dist-info/LICENSE
snxtray-0.0.7.dist-info/METADATA
snxtray-0.0.7.dist-info/WHEEL
snxtray-0.0.7.dist-info/top_level.txt
snxtray-0.0.7.dist-info/RECORD
